setup.py
correios_frete/__init__.py
correios_frete/client.py
correios_frete/constants.py
correios_frete/item.py
correios_frete/package.py
correios_frete/service.py
correios_frete/utils.py
correios_frete/version.py
correios_frete.egg-info/PKG-INFO
correios_frete.egg-info/SOURCES.txt
correios_frete.egg-info/dependency_links.txt
correios_frete.egg-info/requires.txt
correios_frete.egg-info/top_level.txt