Metadata-Version: 1.1
Name: correios-frete
Version: 1.0.0
Summary: Cliente para o WebService de consulta de frete dos correios.
Home-page: https://github.com/adonescunha/correios-frete
Author: Adones Cunha
Author-email: adonescunha@gmail.com
License: UNKNOWN
Platform: UNKNOWN
Classifier: Development Status :: 5 - Production/Stable
Classifier: Intended Audience :: Developers
Classifier: License :: OSI Approved :: MIT License
Classifier: Natural Language :: English
Classifier: Operating System :: OS Independent
Classifier: Programming Language :: Python
